Metadata-Version: 1.1
Name: easyGrad
Version: 1.0.0
Summary: A python package to do auto differentiation.
Home-page: http://packages.python.org/easyGrad
Author: Amartya Sanyal
Author-email: amartya18x@gmail.com
License: License.md
Keywords: autodiff machine-learning deep learning
Platform: UNKNOWN
Classifier: Development Status :: 4 - Beta
Classifier: Intended Audience :: Science/Research
Classifier: License :: OSI Approved :: Apache Software License
Classifier: Programming Language :: Python :: 2.7
Classifier: Topic :: Software Development :: Libraries :: Python Modules
